livekit/plugins/knowlithic/__init__.py
livekit/plugins/knowlithic/config.py
livekit/plugins/knowlithic/log.py
livekit/plugins/knowlithic/models.py
livekit/plugins/knowlithic/py.typed
livekit/plugins/knowlithic/tts.py
livekit/plugins/knowlithic/version.py
livekit_plugins_knowlithic-0.1.4.dist-info/METADATA
livekit_plugins_knowlithic-0.1.4.dist-info/WHEEL
livekit_plugins_knowlithic-0.1.4.dist-info/entry_points.txt
livekit_plugins_knowlithic-0.1.4.dist-info/RECORD
