Metadata-Version: 2.4
Name: livekit-plugins-knowlithic
Version: 0.1.4
Summary: LiveKit plugin for knowlithic TTS using Knowlithic AI
Author-email: Knowlithic <info@knowlithic.com>
License: MIT
Classifier: Intended Audience :: Developers
Classifier: License :: OSI Approved :: Apache Software License
Classifier: Programming Language :: Python :: 3
Classifier: Programming Language :: Python :: 3 :: Only
Classifier: Programming Language :: Python :: 3.9
Classifier: Programming Language :: Python :: 3.10
Classifier: Topic :: Multimedia :: Sound/Audio
Classifier: Topic :: Multimedia :: Video
Classifier: Topic :: Scientific/Engineering :: Artificial Intelligence
Requires-Python: >=3.9.0
Requires-Dist: aiohttp>=3.8.0
Requires-Dist: livekit-agents>=1.2.2
Requires-Dist: livekit>=1.0.12
Requires-Dist: python-dotenv>=1.0.0
